SeleniumTestability/__init__.py
SeleniumTestability/_version.py
SeleniumTestability/javascript.py
SeleniumTestability/listener.py
SeleniumTestability/logger.py
SeleniumTestability/plugin.py
SeleniumTestability/types.py
SeleniumTestability/js/testability.js
SeleniumTestability/js/testability.js.LICENSE.txt
robotframework_seleniumtestability-2.1.0.dist-info/LICENSE
robotframework_seleniumtestability-2.1.0.dist-info/METADATA
robotframework_seleniumtestability-2.1.0.dist-info/WHEEL
robotframework_seleniumtestability-2.1.0.dist-info/top_level.txt
robotframework_seleniumtestability-2.1.0.dist-info/RECORD
