Metadata-Version: 2.1
Name: robotframework-seleniumtestability
Version: 2.1.0
Summary: SeleniumTestability library that helps speed up tests withasyncronous evens
Home-page: https://github.com/marketsquare/robotframework-seleniumtestability
Author: Jani Mikkonen
Author-email: jani.mikkonen@gmail.com
License: Apache License 2.0
Keywords: robot framework testing automation selenium seleniumlibrarytestability async javascript softwaretesting
Platform: any
Classifier: Development Status :: 3 - Alpha
Classifier: Topic :: Software Development :: Testing
Classifier: Operating System :: OS Independent
Classifier: License :: OSI Approved :: Apache Software License
Classifier: Programming Language :: Python
Classifier: Programming Language :: Python :: 3
Classifier: Programming Language :: Python :: 3.7
Classifier: Programming Language :: Python :: 3.8
Classifier: Topic :: Software Development :: Testing
Classifier: Framework :: Robot Framework
Classifier: Framework :: Robot Framework :: Library
License-File: LICENSE
